{"format":2,"version":"5.5","globals":"17a7e622b62b09ca30239a2f6bd6bb33","files":{"api___init___py":{"hash":"7e0190c11881e54a8b54a421dc1069bf","index":{"nums":[1,0,0,0,0,0,0],"html_filename":"api___init___py.html","relative_filename":"api/__init__.py"}},"api_generics_py":{"hash":"c3d2824a8e29b6ffb7805f4928fa2699","index":{"nums":[1,6,0,0,0,0,0],"html_filename":"api_generics_py.html","relative_filename":"api/generics.py"}},"api_urls_py":{"hash":"b59a1b91f1c7e3f1a1aa3b03b0401178","index":{"nums":[1,6,0,0,0,0,0],"html_filename":"api_urls_py.html","relative_filename":"api/urls.py"}},"api_views_py":{"hash":"77870815b11330f66f9049c8d0c70eb6","index":{"nums":[1,6,0,0,0,0,0],"html_filename":"api_views_py.html","relative_filename":"api/views.py"}}}}